<?xml version="1.0" encoding="UTF-8"?>
<xml>
    <blort>
        <blob>hi</blob>
        <blob>hi</blob>
        <blob>hi</blob>
        <blob>hi</blob>
    </blort>
    <blort>
        <blob>hi</blob>
        <blob>hi</blob>
        <blob>hi</blob>
        <blob>yo!</blob>
        <blob>hi</blob>
        <blob>hi</blob>
        <blob>hi</blob>
        <blob>hi</blob>
    </blort>
    <blort>
        <blob>hi</blob>
        <blob>hi</blob>
 
    </blort> 
    <blort>
        <blob>hi</blob>
        <blob>hi</blob>
        <blob>hi</blob>
        <blob>hi</blob>
        <blob>hi</blob>
        <blob>hi</blob>
    </blort>
     
</xml>
