<?xml version="1.0" encoding="UTF-8"?>
<poem><header invisable='1'>Transcript</header>
<pages num='page 1'>Page 1 of 2</pages>
<invisable text='not seen'>Education and Outreach Division</invisable>
<bolded title='full text'>"Ballad of Booker T.," <author>by Langston Hughes</author>, <date time='month,day,year' num='1'>June 1, 1941</date></bolded>
<ttitle>BALLAD OF BOOKER T.</ttitle>
by
<author>Langston Hughes</author>
<firstpage><character main='1'>Booker T.</character>
Was a practical man.
He said, Till the soil
And learn from the land.
Let down your bucket
Where you are.
Your fate is here
And not afar.
To help yourself
And your fellow man,
Train your head,
Your heart, <underlined num='1'>and your hand.</underlined>
For smartness alone's
Surely not meet—
If you haven't at the same time
Got something to eat.
Thus at Tuskegee
He built a school
With book-learning there
And the workman's tool.
He started out
In a simple way—
For yesterday
Was <underlined num='2'>not</underlined> today.
Sometimes he had
Compromise in his talk—
For a man must crawl
Before he can walk—
And in <person famous='president'>Alabama</person> in '85
A joker was lucky
To be alive.
But <character main='1'>Booker T.</character>
Was nobody's fool:
You may carve a dream
With an humble tool.
The tallest tower
Can tumble down
If it be not rooted
In solid ground.
So, being a far-seeing</firstpage>
<secondpage><header invisable='2'>Transcript</header>
<pages num='page 2'>Page 2 of 2</pages>
<text>Education and Outreach Division</text>
Practical man,
He said, Train your head,
Your heart, <underlined num='3'>and your hand.</underlined>
Your fate is here
And not afar,
So let down your bucket
Where you are.
<person>LANGSTON HUGHES</person>
Final Draft,
<place>Hollow Hills Farm,</place>
<city>Monterey</city>, <state usa='1'>California</state>,
<date time='month,day,year' num='2'>June 1, 1941.</date>
<source>Citation: Drafts of <author>Langston Hughes's</author> poem <title poem='reference'>"Ballad of Booker T.,"</title> <time num='day,month,day,month,year'>30 May–1 June 1941.</time></source>
<collection author='1'>(Langston Hughes Collection)</collection> Manuscript Division, <place famouslocation='1'>Library of Congress</place>, <capitial>Washington, D.C.</capitial> 
</secondpage></poem>